ImageDiffOps.py
ImageDiffOps-0.0.1.dist-info/METADATA
ImageDiffOps-0.0.1.dist-info/WHEEL
ImageDiffOps-0.0.1.dist-info/top_level.txt
ImageDiffOps-0.0.1.dist-info/RECORD
